blobber/__init__.py
blobber/blobber.py
blobber/blobber_constants.py
blobber-1.0.dist-info/LICENSE
blobber-1.0.dist-info/METADATA
blobber-1.0.dist-info/WHEEL
blobber-1.0.dist-info/top_level.txt
blobber-1.0.dist-info/RECORD
